ecoinvent_interface/__init__.py
ecoinvent_interface/core.py
ecoinvent_interface/mapping.py
ecoinvent_interface/process_interface.py
ecoinvent_interface/release.py
ecoinvent_interface/settings.py
ecoinvent_interface/spold_versions.py
ecoinvent_interface/storage.py
ecoinvent_interface/string_distance.py
ecoinvent_interface/data/mappings.zip
ecoinvent_interface-3.1.dist-info/LICENSE
ecoinvent_interface-3.1.dist-info/METADATA
ecoinvent_interface-3.1.dist-info/WHEEL
ecoinvent_interface-3.1.dist-info/top_level.txt
ecoinvent_interface-3.1.dist-info/RECORD
