Metadata-Version: 2.2
Name: ecoinvent_interface
Version: 3.1
Summary: Unofficial client for interfacing with ecoinvent database
Author-email:  Chris Mutel <cmutel@gmail.com>
Maintainer-email:  Chris Mutel <cmutel@gmail.com>
Project-URL: source, https://github.com/brightway-lca/ecoinvent_interface
Project-URL: homepage, https://github.com/brightway-lca/ecoinvent_interface
Project-URL: tracker, https://github.com/brightway-lca/ecoinvent_interface/issues
Classifier: Intended Audience :: Science/Research
Classifier: License :: OSI Approved :: BSD License
Classifier: Natural Language :: English
Classifier: Programming Language :: Python :: 3
Classifier: Operating System :: OS Independent
Classifier: Topic :: Scientific/Engineering
Requires-Python: >=3.8
License-File: LICENSE
Requires-Dist: lxml
Requires-Dist: platformdirs
Requires-Dist: py7zr
Requires-Dist: pydantic-settings
Requires-Dist: pyecospold
Requires-Dist: requests
Requires-Dist: tqdm
Provides-Extra: testing
Requires-Dist: ecoinvent_interface; extra == "testing"
Requires-Dist: pypdf; extra == "testing"
Requires-Dist: pytest; extra == "testing"
Requires-Dist: pytest-cov; extra == "testing"
Requires-Dist: setuptools; extra == "testing"
Provides-Extra: dev
Requires-Dist: build; extra == "dev"
Requires-Dist: pre-commit; extra == "dev"
Requires-Dist: pylint; extra == "dev"
Requires-Dist: pypdf; extra == "dev"
Requires-Dist: pytest; extra == "dev"
Requires-Dist: pytest-cov; extra == "dev"
Requires-Dist: setuptools; extra == "dev"
